djangocms_deleted_pages/__init__.py
djangocms_deleted_pages/apps.py
djangocms_deleted_pages/constants.py
djangocms_deleted_pages/utils.py
djangocms_deleted_pages-1.0.1.dist-info/METADATA
djangocms_deleted_pages-1.0.1.dist-info/WHEEL
djangocms_deleted_pages-1.0.1.dist-info/top_level.txt
djangocms_deleted_pages-1.0.1.dist-info/RECORD
