Metadata-Version: 2.4
Name: djangocms-deleted-pages
Version: 1.0.1
Summary: Copy the page to the trash before deleting it.
Author-email: Zdeněk Böhm <zdenek.bohm@nic.cz>
License-Expression: BSD-3-Clause
Project-URL: Homepage, https://gitlab.nic.cz/djangocms-apps/djangocms-deleted-pages
Project-URL: Repository, https://gitlab.nic.cz/djangocms-apps/djangocms-deleted-pages.git
Project-URL: Changelog, https://gitlab.nic.cz/djangocms-apps/djangocms-deleted-pages/-/blob/main/CHANGELOG.md
Classifier: Development Status :: 5 - Production/Stable
Classifier: Framework :: Django
Classifier: Framework :: Django :: 4.2
Classifier: Framework :: Django :: 5.0
Classifier: Framework :: Django :: 5.1
Classifier: Framework :: Django :: 5.2
Classifier: Framework :: Django CMS
Classifier: Framework :: Django CMS :: 4.1
Classifier: Framework :: Django CMS :: 5.0
Classifier: Programming Language :: Python :: 3 :: Only
Classifier: Programming Language :: Python :: 3.9
Classifier: Programming Language :: Python :: 3.10
Classifier: Programming Language :: Python :: 3.11
Classifier: Programming Language :: Python :: 3.12
Classifier: Programming Language :: Python :: 3.13
Requires-Python: >=3.9
Requires-Dist: django-cms<6,>=4.0
Provides-Extra: quality
Requires-Dist: ruff; extra == "quality"
Requires-Dist: mypy; extra == "quality"
